LICENSE
MANIFEST.in
README.md
pyproject.toml
setup.py
./LICENSE
./README.md
danielutils/__init__.py
danielutils/aliases.py
danielutils/colors.py
danielutils/convenience.py
danielutils/custom_types.py
danielutils/date.py
danielutils/date_time.py
danielutils/exceptions.py
danielutils/internet.py
danielutils/io_.py
danielutils/path.py
danielutils/print_.py
danielutils/py.typed
danielutils/random_.py
danielutils/text.py
danielutils/time.py
danielutils/versioned_imports.py
danielutils.egg-info/PKG-INFO
danielutils.egg-info/SOURCES.txt
danielutils.egg-info/dependency_links.txt
danielutils.egg-info/top_level.txt
danielutils/abstractions/__init__.py
danielutils/abstractions/repl.py
danielutils/abstractions/db/__init__.py
danielutils/abstractions/db/database.py
danielutils/abstractions/db/database_definitions.py
danielutils/abstractions/db/database_exceptions.py
danielutils/abstractions/db/database_factory.py
danielutils/abstractions/db/database_initializer.py
danielutils/abstractions/db/database_models.py
danielutils/abstractions/db/dependencies.py
danielutils/abstractions/db/implementations/__init__.py
danielutils/abstractions/db/implementations/in_memory_database.py
danielutils/abstractions/db/implementations/persistent_in_memory_database.py
danielutils/abstractions/db/implementations/redis_database.py
danielutils/abstractions/db/implementations/sqlite_database.py
danielutils/abstractions/multiprogramming/__init__.py
danielutils/abstractions/multiprogramming/multi_id.py
danielutils/abstractions/multiprogramming/worker.py
danielutils/abstractions/multiprogramming/worker_pool.py
danielutils/async_/__init__.py
danielutils/async_/async_cmd.py
danielutils/async_/async_command.py
danielutils/async_/async_layered_command.py
danielutils/async_/async_retry_executor.py
danielutils/async_/async_worker_pool.py
danielutils/async_/time_strategy.py
danielutils/async_/utils.py
danielutils/better_builtins/__init__.py
danielutils/better_builtins/counter.py
danielutils/better_builtins/frange.py
danielutils/better_builtins/typed_builtins/__init__.py
danielutils/better_builtins/typed_builtins/factory.py
