Metadata-Version: 2.4
Name: danielutils
Version: 1.1.23
Summary: A comprehensive Python utilities library providing type-safe collections, async programming tools, database abstractions, retry executors, data structures, and developer productivity enhancements to streamline Python development workflows
Author-email: danielnachumdev <danielnachumdev@gmail.com>
License: MIT License
Project-URL: Homepage, https://github.com/danielnachumdev/danielutils
Project-URL: Bug Tracker, https://github.com/danielnachumdev/danielutils/issues
Classifier: Development Status :: 3 - Alpha
Classifier: Intended Audience :: Developers
Classifier: Programming Language :: Python :: 3
Classifier: Operating System :: Microsoft :: Windows
Requires-Python: >=3.8.0
License-File: LICENSE
Dynamic: license-file
